LICENSE
MANIFEST.in
README.md
requirements.txt
setup.py
examples/__init__.py
examples/app.py
examples/app_only.py
examples/app_slave.py
examples/connection_only.py
examples/controller_only.py
examples/database.py
examples/intersections.py
examples/kinesis_example.py
examples/ramps.py
examples/sqs_example.py
examples/web_only.py
motorway/__init__.py
motorway/connection.py
motorway/controller.py
motorway/decorators.py
motorway/exceptions.py
motorway/grouping.py
motorway/hash_ring.py
motorway/instrumentation.py
motorway/intersection.py
motorway/messages.py
motorway/mixins.py
motorway/pipeline.py
motorway/ramp.py
motorway/threads.py
motorway/utils.py
motorway/webserver.py
motorway.egg-info/PKG-INFO
motorway.egg-info/SOURCES.txt
motorway.egg-info/dependency_links.txt
motorway.egg-info/not-zip-safe
motorway.egg-info/requires.txt
motorway.egg-info/top_level.txt
motorway/contrib/__init__.py
motorway/contrib/amazon_kinesis/__init__.py
motorway/contrib/amazon_kinesis/intersections.py
motorway/contrib/amazon_kinesis/ramps.py
motorway/contrib/amazon_sqs/__init__.py
motorway/contrib/amazon_sqs/exceptions.py
motorway/contrib/amazon_sqs/intersections.py
motorway/contrib/amazon_sqs/mixins.py
motorway/contrib/amazon_sqs/ramps.py
motorway/contrib/amazon_sqs/utils.py
motorway/contrib/recurly_integration/__init__.py
motorway/contrib/recurly_integration/ramps.py
motorway/contrib/salesforce/__init__.py
motorway/contrib/salesforce/intersections.py
motorway/contrib/salesforce/ramps.py
motorway/contrib/sql_alchemy/__init__.py
motorway/contrib/sql_alchemy/intersections.py
motorway/templates/app.js
motorway/templates/app.jsx
motorway/templates/detail.html
motorway/templates/index.html
motorway/templates/style.css
motorway/templates/utils.js
motorway/tests/__init__.py
motorway/tests/sample_pipeline.py
motorway/tests/test_amazon_kinesis.py
motorway/tests/test_controller.py
motorway/tests/test_pipeline.py
motorway/tests/test_utils.py
motorway/tests/utils.py