Metadata-Version: 2.1
Name: motorway
Version: 3.0.4
Summary: Real-time ZMQ-based pure python data pipeline
Home-page: UNKNOWN
Author: Kristian Øllegaard
Author-email: kristian@plecto.com
License: UNKNOWN
Platform: UNKNOWN
License-File: LICENSE
